jitapi/__init__.py
jitapi/__main__.py
jitapi/main.py
jitapi/execution/__init__.py
jitapi/execution/auth_handler.py
jitapi/execution/http_executor.py
jitapi/execution/schema_formatter.py
jitapi/execution/workflow_executor.py
jitapi/ingestion/__init__.py
jitapi/ingestion/embedder.py
jitapi/ingestion/graph_builder.py
jitapi/ingestion/indexer.py
jitapi/ingestion/parser.py
jitapi/mcp/__init__.py
jitapi/mcp/models.py
jitapi/mcp/resources.py
jitapi/mcp/server.py
jitapi/mcp/tools.py
jitapi/retrieval/__init__.py
jitapi/retrieval/graph_expander.py
jitapi/retrieval/reranker.py
jitapi/retrieval/vector_search.py
jitapi/stores/__init__.py
jitapi/stores/graph_store.py
jitapi/stores/spec_store.py
jitapi/stores/vector_store.py
jitapi-0.1.1.dist-info/METADATA
jitapi-0.1.1.dist-info/WHEEL
jitapi-0.1.1.dist-info/entry_points.txt
jitapi-0.1.1.dist-info/RECORD
