Metadata-Version: 2.4
Name: jitapi
Version: 0.1.1
Summary: Just-in-Time API Orchestration System for LLMs - An MCP server for dynamic API discovery and execution
Project-URL: Homepage, https://github.com/nk3750/jitapi
Project-URL: Documentation, https://github.com/nk3750/jitapi#readme
Project-URL: Repository, https://github.com/nk3750/jitapi
Project-URL: Issues, https://github.com/nk3750/jitapi/issues
License: MIT
Keywords: ai,api,claude,llm,mcp,openapi,orchestration
Classifier: Development Status :: 4 - Beta
Classifier: Intended Audience :: Developers
Classifier: License :: OSI Approved :: MIT License
Classifier: Operating System :: OS Independent
Classifier: Programming Language :: Python :: 3
Classifier: Programming Language :: Python :: 3.11
Classifier: Programming Language :: Python :: 3.12
Classifier: Topic :: Internet :: WWW/HTTP
Classifier: Topic :: Software Development :: Libraries :: Python Modules
Requires-Python: >=3.11
Requires-Dist: chromadb>=0.4.0
Requires-Dist: httpx>=0.25.0
Requires-Dist: mcp>=1.0.0
Requires-Dist: networkx>=3.0
Requires-Dist: openai>=1.0.0
Requires-Dist: openapi-pydantic>=0.4.0
Requires-Dist: pydantic-settings>=2.0.0
Requires-Dist: pydantic>=2.0.0
Requires-Dist: python-dotenv>=1.0.0
Requires-Dist: pyyaml>=6.0
Provides-Extra: dev
Requires-Dist: pytest-asyncio>=0.21.0; extra == 'dev'
Requires-Dist: pytest>=7.0.0; extra == 'dev'
Requires-Dist: ruff>=0.1.0; extra == 'dev'
